geomark/__init__.py
geomark/config.py
geomark/geomark.py
geomark/__pycache__/__init__.cpython-36.pyc
geomark/__pycache__/config.cpython-36.pyc
geomark/__pycache__/geomark.cpython-36.pyc
geomark-0.1.1.dist-info/DESCRIPTION.rst
geomark-0.1.1.dist-info/METADATA
geomark-0.1.1.dist-info/RECORD
geomark-0.1.1.dist-info/WHEEL
geomark-0.1.1.dist-info/metadata.json
geomark-0.1.1.dist-info/top_level.txt
tests/__init__.py
tests/conftest.py
tests/data.py
tests/test_geomark.py
