Metadata-Version: 2.0
Name: geomark
Version: 0.1.1
Summary: Tools for manipulating Geomark datasets
Home-page: https://github.com/pauperpythonistas/python-geomark/
Author: Adam Valair, Greg Sebastian
Author-email: adam@bitspatial.com, gregseb@protonmail.com
License: BSD2
Download-URL: https://github.com/pauperpythonistas/python-geomark/archive/0.1.1.tar.gz
Platform: UNKNOWN
Classifier: Environment :: Console
Classifier: Intended Audience :: Developers
Classifier: Intended Audience :: End Users/Desktop
Classifier: Intended Audience :: Science/Research
Classifier: License :: OSI Approved :: BSD License
Classifier: Operating System :: OS Independent
Classifier: Programming Language :: Python
Classifier: Programming Language :: Python :: 2.7
Classifier: Programming Language :: Python :: 3
Classifier: Programming Language :: Python :: 3.4
Classifier: Programming Language :: Python :: 3.5
Classifier: Programming Language :: Python :: 3.6
Classifier: Programming Language :: Python :: 3.7
Classifier: Topic :: Internet :: WWW/HTTP
Classifier: Topic :: Scientific/Engineering :: GIS
Requires-Dist: requests (<2.19.0,>=2.18.1)
